pyGCS/GCI.py
pyGCS/GCS.py
pyGCS/__init__.py
pyGCS-1.1.1.dist-info/LICENSE
pyGCS-1.1.1.dist-info/METADATA
pyGCS-1.1.1.dist-info/WHEEL
pyGCS-1.1.1.dist-info/top_level.txt
pyGCS-1.1.1.dist-info/RECORD
