Metadata-Version: 2.1
Name: pyGCS
Version: 1.1.1
Summary: A package to establish grid independent results for numerical analysis on computational grids.
Home-page: https://github.com/tomrobin-teschner/pyGCS
Author: Tom-Robin Teschner
Author-email: tomrobin.teschner@yahoo.de
Project-URL: Bug Tracker, https://github.com/tomrobin-teschner/pyGCS/issues
Classifier: Programming Language :: Python :: 3
Classifier: License :: OSI Approved :: MIT License
Classifier: Operating System :: OS Independent
Requires-Python: >=3.6
License-File: LICENSE
